lla_enu/__init__.py
lla_enu/utils.py
lla_enu-0.1.0.dist-info/METADATA
lla_enu-0.1.0.dist-info/WHEEL
lla_enu-0.1.0.dist-info/top_level.txt
lla_enu-0.1.0.dist-info/RECORD
